hoggormplot/SMI_plot.py
hoggormplot/__init__.py
hoggormplot/conv_biPlot.py
hoggormplot/conv_coefficientsPlot.py
hoggormplot/conv_correlationLoadingsPlot.py
hoggormplot/conv_explainedVariancePlot.py
hoggormplot/conv_loadingWeightsPlot.py
hoggormplot/conv_loadingsPlot.py
hoggormplot/conv_predictPlot.py
hoggormplot/conv_scoresPlot.py
hoggormplot/data.py
hoggormplot/main_plot.py
hoggormplot/version.py
hoggormplot-0.13.2.dist-info/LICENSE
hoggormplot-0.13.2.dist-info/METADATA
hoggormplot-0.13.2.dist-info/WHEEL
hoggormplot-0.13.2.dist-info/top_level.txt
hoggormplot-0.13.2.dist-info/RECORD
